LICENSE
MANIFEST.in
README.rst
rofi.py
setup.cfg
setup.py
papis_python_rofi.egg-info/PKG-INFO
papis_python_rofi.egg-info/SOURCES.txt
papis_python_rofi.egg-info/dependency_links.txt
papis_python_rofi.egg-info/top_level.txt
papis_python_rofi.egg-info/zip-safe