Metadata-Version: 1.1
Name: papis-python-rofi
Version: 1.0.2
Summary: Create simple GUIs using the Rofi application (fork for papis)
Home-page: https://github.com/alejandrogallo/python-rofi
Author: Blair Bonnett
Author-email: blair.bonnett@gmail.com
License: MIT
Platform: UNKNOWN
Classifier: License :: OSI Approved :: MIT License
Classifier: Programming Language :: Python
Classifier: Development Status :: 5 - Production/Stable
